odoo/addons/agreement_helpdesk_mgmt_serviceprofile/README.rst
odoo/addons/agreement_helpdesk_mgmt_serviceprofile/__init__.py
odoo/addons/agreement_helpdesk_mgmt_serviceprofile/__manifest__.py
odoo/addons/agreement_helpdesk_mgmt_serviceprofile/i18n/agreement_helpdesk_mgmt_serviceprofile.pot
odoo/addons/agreement_helpdesk_mgmt_serviceprofile/i18n/it.po
odoo/addons/agreement_helpdesk_mgmt_serviceprofile/i18n/sv.po
odoo/addons/agreement_helpdesk_mgmt_serviceprofile/models/__init__.py
odoo/addons/agreement_helpdesk_mgmt_serviceprofile/models/helpdesk_ticket.py
odoo/addons/agreement_helpdesk_mgmt_serviceprofile/readme/CONTRIBUTORS.md
odoo/addons/agreement_helpdesk_mgmt_serviceprofile/readme/DESCRIPTION.md
odoo/addons/agreement_helpdesk_mgmt_serviceprofile/static/description/icon.png
odoo/addons/agreement_helpdesk_mgmt_serviceprofile/static/description/index.html
odoo/addons/agreement_helpdesk_mgmt_serviceprofile/views/helpdesk_ticket.xml
odoo_addon_agreement_helpdesk_mgmt_serviceprofile-18.0.1.0.0.6.dist-info/METADATA
odoo_addon_agreement_helpdesk_mgmt_serviceprofile-18.0.1.0.0.6.dist-info/WHEEL
odoo_addon_agreement_helpdesk_mgmt_serviceprofile-18.0.1.0.0.6.dist-info/top_level.txt
odoo_addon_agreement_helpdesk_mgmt_serviceprofile-18.0.1.0.0.6.dist-info/RECORD
